covermi/__init__.py
covermi/annotate.py
covermi/annotatetsca.py
covermi/bringmiup.py
covermi/cache.py
covermi/clinicalreport.py
covermi/cov.py
covermi/covermigui.py
covermi/covermimain.py
covermi/covermiplot (copy).py
covermi/covermiplot.py
covermi/covermiwgsgui.py
covermi/covermiwgsmain.py
covermi/designreport.py
covermi/gr.py
covermi/include.py
covermi/panel.py
covermi/reportfunctions.py
covermi/tablereport.py
covermi/technicalreport.py
covermi-3.1.2.dist-info/METADATA
covermi-3.1.2.dist-info/RECORD
covermi-3.1.2.dist-info/WHEEL
covermi-3.1.2.dist-info/entry_points.txt
covermi-3.1.2.dist-info/top_level.txt
covermi-3.1.2.dist-info/zip-safe
