Metadata-Version: 2.1
Name: covermi
Version: 3.1.2
Summary: Coverage checking for next generation sequencing panels
Home-page: http://github.com/eawilson/covermi
Author: Ed Wilson
Author-email: edwardadrianwilson@yahoo.co.uk
License: MIT
Platform: UNKNOWN
